simrpc/__init__.py
simrpc/client.py
simrpc/message.py
simrpc/server.py
simrpc-1.3.1.dist-info/LICENSE
simrpc-1.3.1.dist-info/METADATA
simrpc-1.3.1.dist-info/WHEEL
simrpc-1.3.1.dist-info/top_level.txt
simrpc-1.3.1.dist-info/RECORD
