Metadata-Version: 2.1
Name: simrpc
Version: 1.3.1
Summary: README.md
Home-page: https://github.com/aohan237/simrpc
Author: aohan237
Author-email: aohan237@gmail.com
License: BSD
Keywords: rpc asyncio zeromq msgpack
Platform: any
Classifier: Development Status :: 5 - Production/Stable
Classifier: License :: OSI Approved :: BSD License
Classifier: Programming Language :: Python
Classifier: Programming Language :: Python :: 2
Classifier: Programming Language :: Python :: 2.7
Classifier: Programming Language :: Python :: 3
Classifier: Programming Language :: Python :: 3.5
Classifier: Programming Language :: Python :: 3.6
Classifier: Programming Language :: Python :: 3.7
Classifier: Programming Language :: Python :: Implementation :: CPython
Classifier: Programming Language :: Python :: Implementation :: PyPy
Classifier: Operating System :: OS Independent
Classifier: Topic :: Communications
Classifier: Topic :: System :: Distributed Computing
Classifier: Topic :: Software Development :: Libraries :: Python Modules
Requires-Dist: pyzmq (>=17.1.2)
Requires-Dist: msgpack (>=0.5.6)
